apiron/__init__.py
apiron/client.py
apiron/exceptions.py
apiron/py.typed
apiron/endpoint/__init__.py
apiron/endpoint/endpoint.py
apiron/endpoint/json.py
apiron/endpoint/streaming.py
apiron/endpoint/stub.py
apiron/service/__init__.py
apiron/service/base.py
apiron/service/discoverable.py
apiron-9.1.0.dist-info/licenses/LICENSE
apiron-9.1.0.dist-info/METADATA
apiron-9.1.0.dist-info/WHEEL
apiron-9.1.0.dist-info/top_level.txt
apiron-9.1.0.dist-info/RECORD
