Metadata-Version: 2.4
Name: apiron
Version: 9.1.0
Summary: apiron helps you cook a tasty client for RESTful APIs. Just don't wash it with SOAP.
Author-email: "Ithaka Harbors, Inc." <opensource@ithaka.org>
License: Copyright 2018-2025 Ithaka Harbors, Inc.
Project-URL: Repository, https://github.com/ithaka/apiron
Project-URL: Changelog, https://github.com/ithaka/apiron/blob/main/CHANGELOG.md
Project-URL: Documentation, https://apiron.readthedocs.io
Project-URL: Issues, https://github.com/ithaka/apiron/issues
Classifier: Development Status :: 5 - Production/Stable
Classifier: Intended Audience :: Developers
Classifier: Topic :: Internet :: WWW/HTTP
Classifier: Topic :: Software Development :: Libraries :: Python Modules
Classifier: Programming Language :: Python
Classifier: Programming Language :: Python :: 3.10
Classifier: Programming Language :: Python :: 3.11
Classifier: Programming Language :: Python :: 3.12
Classifier: Programming Language :: Python :: 3.13
Classifier: Programming Language :: Python :: 3
Classifier: Programming Language :: Python :: 3 :: Only
Classifier: License :: OSI Approved :: MIT License
License-File: LICENSE
Requires-Dist: requests>=2.11.1
Requires-Dist: urllib3>=1.26.13
Provides-Extra: docs
Requires-Dist: sphinx>=7.2.2; extra == "docs"
Requires-Dist: sphinx-autobuild>=2021.3.14; extra == "docs"
Dynamic: license-file
